[{"liner":"OZBLFAeFfVOh","first_port":"jHTGWBxsyBXn","last_port":"bLfLXVnWylRW","price":"3628"},{"liner":"StxQGOyLOdpu","first_port":"SAHNbYMvDocG","last_port":"rTjuDxfAxnIh","price":"1192"},{"liner":"PLWhhptadUaD","first_port":"NgEXTAnoVXxb","last_port":"MqYaycquVmqg","price":"1145"},{"liner":"pWdtynoxflMm","first_port":"vAqxeXjZoGGH","last_port":"mljbTyhEplfs","price":"6276"},{"liner":"PiVJwtiWzBIA","first_port":"RhNisrNWwPJL","last_port":"jMMWoBoEDsyL","price":"9667"},{"liner":"rYYkhiwrjuof","first_port":"wfivgwBXhqaY","last_port":"rfcJxKGXjCDw","price":"2414"},{"liner":"gIZuoUsNpiPL","first_port":"ELeFWykMJmci","last_port":"MXLisAKnYvKs","price":"8033"},{"liner":"JtFKNTmZsPqp","first_port":"WBDeiognhgig","last_port":"DEHiKApbkypS","price":"4014"},{"liner":"bhmAtDAVPuzx","first_port":"AWLZueYfxnsp","last_port":"GKYrXFkOVnHj","price":"6949"},{"liner":"QOlQZfmYLDtV","first_port":"MTtVPZHlXZbl","last_port":"zxbAJdDgzsAU","price":"9978"},{"liner":"ThaJNNXjaIZR","first_port":"OqbUccKMOnBH","last_port":"ExwQoHjuwtws","price":"7096"},{"liner":"hjhmQDJJxRXv","first_port":"xRmrLlJRocye","last_port":"bjhuSilyyHsQ","price":"0876"},{"liner":"XtxJQiaCXvxH","first_port":"RPzCfmcafnkM","last_port":"BZmsrWRpbmIE","price":"7413"},{"liner":"aAfDexWBDQNw","first_port":"XtODRUERcckf","last_port":"nVSoYvgLIJXu","price":"7764"},{"liner":"fwGbfIvhZoul","first_port":"YcjtgnCXxICK","last_port":"MiVcFUUfTZSl","price":"7195"},{"liner":"vodFuENCTzTd","first_port":"aXvcoBgywCTg","last_port":"oWINFDZMxzPp","price":"8579"},{"liner":"kBRkDjpDfDQk","first_port":"IZvLQZZzJcyo","last_port":"qVUgqQyggPAU","price":"5985"},{"liner":"ASjktUrIlTjK","first_port":"kZrJXMCOxvQp","last_port":"GmMZpGIZSByt","price":"4245"},{"liner":"FIdFJkBHuhjf","first_port":"GOPhvdqdkyEa","last_port":"WrIZjtpEFGdY","price":"4349"},{"liner":"cIbzunmDRcNf","first_port":"wNHymRIclUzU","last_port":"BnbuVXRyJNMD","price":"0450"},{"liner":"ShARbvHfuhom","first_port":"TVwkcvbofwEA","last_port":"mxFXSTVxHQuP","price":"2477"},{"liner":"wYwfoEIOAsPf","first_port":"anOFejMJAbhF","last_port":"qarRqegyZBqP","price":"2967"},{"liner":"HvlttcgpzEbn","first_port":"AAJXCpzbbyQt","last_port":"neREAQNNKheH","price":"7460"},{"liner":"ezhyRcFxGPFR","first_port":"kNFjOXowvfNJ","last_port":"aUzMdlxVfXiS","price":"1050"},{"liner":"kzJNIrXSokak","first_port":"YjRegdftrMRE","last_port":"PKyRytdFUxhT","price":"7050"},{"liner":"PVworKRlBoqG","first_port":"EmytOcTXDCKZ","last_port":"QlkmhtkDESSr","price":"0974"},{"liner":"PCEwvlZrKRqE","first_port":"CBRAKbIUlsLD","last_port":"uAYwwTHiETFD","price":"0735"},{"liner":"ybekxpaULIpp","first_port":"qAbuUlaAeWBw","last_port":"JUGzxTKZRtSD","price":"3869"},{"liner":"uJVjVdtcJoaw","first_port":"ygkMjtlAmEMH","last_port":"NMjKRFBxDwwu","price":"1685"},{"liner":"pmHRDGAWvaQo","first_port":"giQJLfgULNEh","last_port":"CEgyjkDMtHiM","price":"7434"},{"liner":"eGTBzjOfTYHb","first_port":"uLIqtJtASAhB","last_port":"GtIwXnnxiMxb","price":"3066"},{"liner":"EfnTZYKCYBuo","first_port":"mozqpgizcxtn","last_port":"xtzUSVrqufIx","price":"7376"},{"liner":"GZnqfCvGikQY","first_port":"UNEffnGRgKcj","last_port":"DQKQdljLxtrP","price":"0450"},{"liner":"RLVmPOIapuLM","first_port":"ysCUZkegSGtl","last_port":"ulJolwEJEnji","price":"8235"},{"liner":"tPDBlrrHQfKL","first_port":"HtmlIfvxDxNM","last_port":"TIyJBIRFhKOk","price":"7104"},{"liner":"dqdyWfeJyoFE","first_port":"XITQpuaJGsax","last_port":"QkZcZtrwLUWq","price":"3871"},{"liner":"kezWvyxRKjaw","first_port":"uFjakXVpRTPb","last_port":"SnzirWxOvcOJ","price":"2634"},{"liner":"SmLtHJCvnpSq","first_port":"oFVfhHnjwZSZ","last_port":"LsjMZwdakPKp","price":"1106"},{"liner":"RfmRUOeZRZqx","first_port":"CsIARIbHfLCI","last_port":"pFOmMagnCOPt","price":"0060"},{"liner":"wZGpdsgksCfU","first_port":"wzpdOvHNykJg","last_port":"MhNPgpgpCYue","price":"6833"},{"liner":"tLYTZIiqdVVZ","first_port":"mtCjAkgrergB","last_port":"JaxGTqZdbdVa","price":"2447"},{"liner":"xOoTzmoPNzIF","first_port":"ekyxfVqxBHPU","last_port":"mcNzFcIEkjRV","price":"3319"},{"liner":"VMBTaAkDtEDz","first_port":"ZkRACGUumhuf","last_port":"XnLWDLbVuKqn","price":"7485"},{"liner":"wzXlCbpHVusq","first_port":"keOMxNnIaADE","last_port":"QakbKPgZhJPD","price":"6861"},{"liner":"SnkWuZomdWjv","first_port":"zJGBFXoJrkSo","last_port":"hKtEdiiAnDfR","price":"8885"},{"liner":"RLOVSZQLxwnZ","first_port":"KFeQcGNuPtEy","last_port":"HeZlvTqeVWQm","price":"5255"},{"liner":"jmUnhDTxzqKZ","first_port":"JhmWotcONnxT","last_port":"UNySXrUESYOp","price":"9324"},{"liner":"PEoQXnZrExLA","first_port":"HVqwMPpPWiOV","last_port":"qtnbjEhINDTf","price":"6441"},{"liner":"xQFHtYvuWAsr","first_port":"kmDsJAxdcFoD","last_port":"hqgmvoTfqnhN","price":"1921"},{"liner":"DkDNoartCLNz","first_port":"uWJsuecCOafD","last_port":"MnRylbxnYqBQ","price":"2552"},{"liner":"qmqloCeNJhLw","first_port":"pyksHSalAshc","last_port":"aeAgaUHUcIRN","price":"6899"},{"liner":"rbxfMJQRHfQN","first_port":"aKwTdAXqqCOE","last_port":"hDaTcvOOpQxC","price":"2641"},{"liner":"yNKCzVELZZwf","first_port":"bKFJlBnKHXIa","last_port":"NAEfHXOkxWym","price":"8761"},{"liner":"FmlEqSiTRtBs","first_port":"PdTIJGMXrqkv","last_port":"sgkQMqEkLSZg","price":"6387"},{"liner":"TSKhHNDgCmIw","first_port":"JvQOdEsuVbHv","last_port":"kSwWLTYPwOeO","price":"2207"},{"liner":"vZXLQvZBTXPe","first_port":"QXbyBkRsEnni","last_port":"dwdreMZTatmz","price":"5610"},{"liner":"ZqoZHVRfxiYD","first_port":"OoBmfVDOEoXf","last_port":"BxOHgjMQlsfT","price":"5871"},{"liner":"jpdCFfxOETwf","first_port":"cCMnAjXSzRzL","last_port":"VrocqEdfSDsr","price":"9133"},{"liner":"screkxwXvxzU","first_port":"OLdvnBhOQerO","last_port":"pzpyUwvJgQtP","price":"1714"},{"liner":"WjhdLaLRefve","first_port":"QAaEuTEyzehY","last_port":"hMFITbFYxlKT","price":"6079"},{"liner":"CPpCZwGtltWK","first_port":"cHvHKaYiekMP","last_port":"PEudGhQeYbat","price":"3242"},{"liner":"vQBAszdMlknr","first_port":"fSLeypPUzNHQ","last_port":"nPFvBRsvFHfJ","price":"2189"},{"liner":"WvwbpmmWmgvq","first_port":"QqdfIvYFxOdQ","last_port":"zrxjBElZyvKW","price":"5837"},{"liner":"cqCJhVdEvEfj","first_port":"zBavJfbWwhUS","last_port":"xdnhphgZskNf","price":"5468"},{"liner":"ROdJdueQLfkg","first_port":"GDVeuACrfqHf","last_port":"dqMEkvSrMtBJ","price":"5143"},{"liner":"WFnLZJHCaRLG","first_port":"SEjTLrAdvYfo","last_port":"oKAtkeYoOdtL","price":"4957"},{"liner":"WDAxwmAfIzzT","first_port":"OkSBxoPeqlai","last_port":"vFiDvOrusUMP","price":"4127"},{"liner":"LpiSKYZNrzZX","first_port":"OAxokuJjYLYF","last_port":"dBTBnJQVXExg","price":"8451"},{"liner":"JJXNKvRrdNpb","first_port":"YoRzbqADPHqX","last_port":"cfMMpcJqWeOr","price":"3796"},{"liner":"MNXgUOOfjFXu","first_port":"ZpCihurMCmSL","last_port":"vrTKxCugJjlE","price":"2666"},{"liner":"nmQeEGdpjCQb","first_port":"TqtVgLZWBwMs","last_port":"ASQvLTURSzMW","price":"0890"},{"liner":"fipkNfCEjeOx","first_port":"VqcmjfuJWRRg","last_port":"rJKcoBZlHjfm","price":"4022"},{"liner":"pxBlCHUfrQXq","first_port":"STMbHVuipJSk","last_port":"IXqyQkFKWzZx","price":"6173"},{"liner":"YTaIittzfiPh","first_port":"zIzgWKozOhfE","last_port":"LccVQyesLSQY","price":"1106"},{"liner":"zyRYKismEPZQ","first_port":"lKjCUKHyaZNb","last_port":"dugDVtTgpOGk","price":"2203"},{"liner":"LfBfxcCVlfVL","first_port":"XTrgMDlqpJOo","last_port":"XTjgLOjGrscY","price":"9285"},{"liner":"bqptvqyYFnKq","first_port":"MSZIKnpHMHlB","last_port":"XrvABUSittFZ","price":"6681"},{"liner":"OKwfWjdWgiAT","first_port":"xHMBGdvmTvhZ","last_port":"ZgQGFdcECbEt","price":"8306"},{"liner":"SQDevivuvFha","first_port":"NWPDyzRNSLkG","last_port":"PcIkHpBrciEb","price":"4886"},{"liner":"hKvSoWvnFfNk","first_port":"RoqKwMJUvioU","last_port":"plmbYNXjOsVW","price":"3288"},{"liner":"cLIgxIQqAtgQ","first_port":"yPNjFcxHacCT","last_port":"jKwIcRDItcAv","price":"9454"},{"liner":"KiXjKKpVSKCu","first_port":"BzkADegwIZHu","last_port":"pmzVuASIYtMy","price":"3227"},{"liner":"DSXgUloRkgxN","first_port":"jhXDYFECBIQE","last_port":"mpoKhVREpxJG","price":"9437"},{"liner":"tAUfAPTsiFit","first_port":"RJmOIxpHkNQp","last_port":"mQxNcmDyMCkO","price":"2238"},{"liner":"tFafsHretfcJ","first_port":"kUFYBJedbCUc","last_port":"mjVnyCajimXT","price":"8843"},{"liner":"zwelPJlGRvbq","first_port":"cefLVdRuhyoU","last_port":"pxGacQJmkVuC","price":"9837"},{"liner":"RAkWvrZcynwg","first_port":"YrJoOsiMsZYl","last_port":"oqDbDJElFbon","price":"3894"},{"liner":"AbbzuvfOuDiZ","first_port":"xXlZBhZjnBMu","last_port":"NAaENDLMcpmd","price":"9881"},{"liner":"ErZXLaBIhsUK","first_port":"BFXrvOvvmVfg","last_port":"boGcynqWCtXO","price":"9534"},{"liner":"EyFxQrgsIjwl","first_port":"CDyDZXbKeXWL","last_port":"ADloxLemYmNf","price":"4520"},{"liner":"HnkVfnLCdywn","first_port":"qNCPOrIHfTTn","last_port":"GnglmjAAzDKu","price":"6270"},{"liner":"edtjFqvEvShb","first_port":"LEusCqvgWVuh","last_port":"JTENNLZKLQIF","price":"7370"},{"liner":"nqONFVbzzjDz","first_port":"cEIVLoFcSxHY","last_port":"iQpXnkDtjZUg","price":"4479"},{"liner":"HdOvCfXGUNgE","first_port":"LDuHKPyeYRlg","last_port":"gUmLGhNRQoFn","price":"6830"},{"liner":"zPESmdWSqFyC","first_port":"AcZOvuHmwycn","last_port":"rXjPsxqeCoRZ","price":"1930"},{"liner":"xILfliERgFlH","first_port":"rARGAnFdulPa","last_port":"CXgFhTwsvAut","price":"9172"},{"liner":"BbRDKOezetpL","first_port":"ilyOlLuMUetr","last_port":"AgdYnEjDYRak","price":"6617"},{"liner":"bdHWuMzaXKby","first_port":"kyOIwUHxUkFs","last_port":"eULNCcEKXjTl","price":"9374"},{"liner":"tzofLWVcXxMj","first_port":"VHqOwuFlrrGh","last_port":"yshdrsihxmVW","price":"9044"}]
